backupradar/__init__.py
backupradar/client.py
backupradar/exceptions.py
backupradar/models.py
backupradar-0.1.7.dist-info/LICENSE
backupradar-0.1.7.dist-info/METADATA
backupradar-0.1.7.dist-info/WHEEL
backupradar-0.1.7.dist-info/RECORD
