Metadata-Version: 2.1
Name: backupradar
Version: 0.1.7
Summary: Python package for interacting with BackupRadar API.
Author: 0xChloe
Author-email: chloe@catastrophesoftware.com
Requires-Python: >=3.10,<4.0
Classifier: Programming Language :: Python :: 3
Classifier: Programming Language :: Python :: 3.10
Classifier: Programming Language :: Python :: 3.11
Classifier: Programming Language :: Python :: 3.12
Classifier: Programming Language :: Python :: 3.13
Requires-Dist: httpx (>=0.27.2,<0.28.0)
Requires-Dist: pydantic (>=2.9.2,<3.0.0)
